repo2vec/__init__.py
repo2vec/chat.py
repo2vec/chunker.py
repo2vec/data_manager.py
repo2vec/embedder.py
repo2vec/github.py
repo2vec/index.py
repo2vec/llm.py
repo2vec/sample-exclude.txt
repo2vec/vector_store.py
tests/__init__.py
tests/conftest.py
tests/test_chunker.py
repo2vec-0.1.8.dist-info/LICENSE
repo2vec-0.1.8.dist-info/METADATA
repo2vec-0.1.8.dist-info/WHEEL
repo2vec-0.1.8.dist-info/entry_points.txt
repo2vec-0.1.8.dist-info/top_level.txt
repo2vec-0.1.8.dist-info/RECORD
