Metadata-Version: 2.1
Name: repo2vec
Version: 0.1.8
Summary: A library to index a code repository and chat with it via LLMs.
Home-page: https://github.com/Storia-AI/repo2vec
Author: Julia Turc & Mihail Eric / Storia AI
Author-email: founders@storia.ai
Classifier: Programming Language :: Python :: 3
Classifier: License :: OSI Approved :: MIT License
Classifier: Operating System :: OS Independent
Requires-Python: >=3.9
License-File: LICENSE
Requires-Dist: GitPython ==3.1.43
Requires-Dist: Pygments ==2.18.0
Requires-Dist: fastapi ==0.112.2
Requires-Dist: gradio >=4.26.0
Requires-Dist: langchain ==0.2.14
Requires-Dist: langchain-community ==0.2.12
Requires-Dist: langchain-anthropic ==0.1.23
Requires-Dist: langchain-ollama ==0.1.2
Requires-Dist: langchain-openai ==0.1.22
Requires-Dist: marqo ==3.7.0
Requires-Dist: nbformat ==5.10.4
Requires-Dist: openai ==1.42.0
Requires-Dist: pinecone ==5.0.1
Requires-Dist: python-dotenv ==1.0.1
Requires-Dist: requests ==2.32.3
Requires-Dist: semchunk ==2.2.0
Requires-Dist: tiktoken ==0.7.0
Requires-Dist: tree-sitter ==0.22.3
Requires-Dist: tree-sitter-language-pack ==0.2.0
Requires-Dist: setuptools
